pms_integration_utils-25.8.dist-info/licenses/LICENSE.txt
pmsintegration/platform/__init__.py
pmsintegration/platform/cli.py
pmsintegration/platform/concurrent_utils.py
pmsintegration/platform/config.py
pmsintegration/platform/credentials.py
pmsintegration/platform/disk_store.py
pmsintegration/platform/dynamic_expr.py
pmsintegration/platform/errors.py
pmsintegration/platform/globals.py
pmsintegration/platform/retries.py
pmsintegration/platform/sshutils.py
pmsintegration/platform/string_cleansing.py
pmsintegration/platform/ttl_cache.py
pmsintegration/platform/unsafe.py
pmsintegration/platform/utils.py
pmsintegration/platform/internal/__init__.py
pmsintegration/platform/internal/python_code_checker.py
pms_integration_utils-25.8.dist-info/METADATA
pms_integration_utils-25.8.dist-info/WHEEL
pms_integration_utils-25.8.dist-info/entry_points.txt
pms_integration_utils-25.8.dist-info/top_level.txt
pms_integration_utils-25.8.dist-info/RECORD
