Metadata-Version: 2.4
Name: pms-integration-utils
Version: 25.8
Summary: PMS Integration Utils
Author-email: Sandeep Kadyan <sandeep.kadyan@corient.com>
License: Proprietary Software (c) 2025-2026 data-integration-libs maintainer.
Classifier: Development Status :: 4 - Beta
Classifier: Natural Language :: English
Classifier: Operating System :: OS Independent
Classifier: Programming Language :: Python :: 3.11
Classifier: Programming Language :: Python :: 3.12
Requires-Python: >=3.11
License-File: LICENSE.txt
Requires-Dist: typer
Requires-Dist: xmlschema
Requires-Dist: fsspec
Requires-Dist: pydantic
Requires-Dist: pydantic-extra-types
Requires-Dist: pendulum
Requires-Dist: pyyaml
Requires-Dist: zstandard
Requires-Dist: sshtunnel
Requires-Dist: tenacity
Provides-Extra: dev
Requires-Dist: pip-tools; extra == "dev"
Requires-Dist: twine; extra == "dev"
Requires-Dist: pre-commit; extra == "dev"
Requires-Dist: Flake8-pyproject; extra == "dev"
Requires-Dist: Flake8-html; extra == "dev"
Requires-Dist: flake8-formatter-junit-xml; extra == "dev"
Requires-Dist: pipdeptree; extra == "dev"
Requires-Dist: tabulate; extra == "dev"
Provides-Extra: test
Requires-Dist: pytest-mock; extra == "test"
Requires-Dist: pytest-cov; extra == "test"
Requires-Dist: pytest-env; extra == "test"
Requires-Dist: pytest-html; extra == "test"
Requires-Dist: flake8-formatter-junit-xml; extra == "test"
Dynamic: license-file
